yadloader/__init__.py
yadloader/main.py
yadloader-0.1.0.dist-info/METADATA
yadloader-0.1.0.dist-info/WHEEL
yadloader-0.1.0.dist-info/entry_points.txt
yadloader-0.1.0.dist-info/licenses/LICENSE
yadloader-0.1.0.dist-info/RECORD
