Metadata-Version: 2.4
Name: yadloader
Version: 0.1.0
Summary: Yet another downloader for those poor souls who have to use Yandex.Disk shared folders to receive big data.
Project-URL: Repository, https://codeberg.org/screwery/yadloader
Project-URL: Issues, https://codeberg.org/screwery/yadloader/issues
Project-URL: Changelog, https://codeberg.org/screwery/yadloader/src/branch/main/CHANGELOG.md
Author-email: Ellie Viesná <snowboard_refinery@proton.me>
License-Expression: MIT
License-File: LICENSE
Keywords: cloud,disk,downloader,folder,shared,yandex
Classifier: Development Status :: 4 - Beta
Classifier: Environment :: Console
Classifier: License :: OSI Approved :: MIT License
Classifier: Natural Language :: English
Classifier: Operating System :: OS Independent
Classifier: Programming Language :: Python :: 3.11
Classifier: Programming Language :: Python :: 3.12
Requires-Python: >=3.11
Requires-Dist: argparse
Requires-Dist: requests
Requires-Dist: tqdm
